scgt/__init__.py
scgt/scgt.py
scgt-0.0.32.dist-info/LICENSE.md
scgt-0.0.32.dist-info/METADATA
scgt-0.0.32.dist-info/WHEEL
scgt-0.0.32.dist-info/top_level.txt
scgt-0.0.32.dist-info/RECORD
