Metadata-Version: 2.1
Name: scgt
Version: 0.0.32
Summary: UC Santa Cruz Geographical Toolkit
Author-email: Jasmine Tai <cjtai@ucsc.edu>, Natalie Valett <nvalett@ucsc.edu>, Luca de Alfaro <luca@dealfaro.com>
License: Copyright 2023, The Regents of the University of California. 
Project-URL: Homepage, https://github.com/ecoscape-earth/scgt
Project-URL: Bug Tracker, https://github.com/ecoscape-earth/scgt/issues
Classifier: Development Status :: 3 - Alpha
Classifier: Intended Audience :: Developers
Classifier: License :: OSI Approved :: BSD License
Classifier: Operating System :: OS Independent
Classifier: Programming Language :: Python :: 3
Classifier: Programming Language :: Python :: Implementation :: CPython
Classifier: Topic :: Software Development :: Libraries :: Python Modules
Requires-Python: >=3.7
License-File: LICENSE.md
Requires-Dist: GDAL >=3.0.0
Requires-Dist: matplotlib >=3.5.3
Requires-Dist: numpy >=1.20.3
Requires-Dist: rasterio >=1.2.10
Requires-Dist: scipy >=1.7.3
